dataprep/QueryFunctions.py
dataprep/__init__.py
dataprep/combine_data.py
dataprep/dprepare.py
dataprep/dprepare_ponfare.py
dataprep/dprepare_ponfare_matching.py
dataprep/dprepare_ponfare_matching_d2dist.py
dataprep/dprepare_uscensus.py
dataprep/dprepare_uscensus_bkup.py
dataprep/dprepare_uscensus_intensity_matching_age.py
dataprep/fix_data.py
dataprep/fix_data_allcohorts.py
dataprep/fix_data_exploreonly_small.py
dataprep/prep_hscls_data.py
dataprep/prep_hscls_data_11wks_workbenchnull.py
dataprep/preproc_ponfare.py
dataprep/pull_data_presto.py
dataprep/readCensus.py
gbdtleaves/__init__.py
gbdtleaves/inc_gbdt.py
gbdtleaves/inc_gbdt_v2.py
gbdtleaves/leaves.py
gbdtleaves/leaves_cpit.py
gbdtleaves/leaves_drm.py
hclctpm/ModelingUtils.py
hclctpm/ModelingUtils_bkup.py
hclctpm/QueryFunctions.py
hclctpm/QueryFunctions_bkup.py
hclctpm/__init__.py
hclctpm/dataprep/DataProcFunctions.py
hclctpm/dataprep/QueryFunctions.py
hclctpm/dataprep/__init__.py
hclctpm/dataprep/combine_data.py
hclctpm/dataprep/dprepare.py
hclctpm/dataprep/dprepare_ponfare.py
hclctpm/dataprep/dprepare_ponfare_matching.py
hclctpm/dataprep/dprepare_ponfare_matching_d2dist.py
hclctpm/dataprep/dprepare_uscensus.py
hclctpm/dataprep/dprepare_uscensus_bkup.py
hclctpm/dataprep/dprepare_uscensus_intensity_matching_age.py
hclctpm/dataprep/fix_data.py
hclctpm/dataprep/fix_data_allcohorts.py
hclctpm/dataprep/fix_data_exploreonly_small.py
hclctpm/dataprep/prep_hscls_data.py
hclctpm/dataprep/prep_hscls_data_11wks_workbenchnull.py
hclctpm/dataprep/preproc_ponfare.py
hclctpm/dataprep/pull_data_presto.py
hclctpm/dataprep/readCensus.py
hclctpm/exp/Experimentation.py
hclctpm/exp/__init__.py
hclctpm/models/CLModel.py
hclctpm/models/LinearHTEModels.py
hclctpm/models/ModelDefinitions.py
hclctpm/models/PromotionModels.py
hclctpm/models/__init__.py
hclctpm/models/bklog.py
hclctpm/models/dummy.py
hclctpm/models/layers_tfv2.py
hclctpm/models/pyMLModelDefinitions.py
hclctpm/models/rlearner.py
hclctpm/models/rxgy.py
hclctpm-0.5.3.dist-info/LICENSE
hclctpm-0.5.3.dist-info/METADATA
hclctpm-0.5.3.dist-info/WHEEL
hclctpm-0.5.3.dist-info/top_level.txt
hclctpm-0.5.3.dist-info/RECORD
