Metadata-Version: 2.1
Name: hclctpm
Version: 0.5.3
Summary: HCLCTPM: Heterogeneous Sequential Casual Learning System.
Home-page: https://github.com/willzyz/hclctpm
Author: Michelangelo Team
Author-email: wzou@alumni.stanford.edu
License: UNKNOWN
Platform: UNKNOWN
